Metadata-Version: 2.4
Name: iflow-mcp_dicklesworthstone_mcp-agent-mail
Version: 0.2.1
Summary: Coordinated multi-agent messaging and coordination MCP server.
Project-URL: Homepage, https://example.com/mcp-agent-mail
Project-URL: Repository, https://example.com/mcp-agent-mail
Author: mcp-agent-mail maintainers
License: MIT
License-File: LICENSE
Classifier: Development Status :: 3 - Alpha
Classifier: Intended Audience :: Developers
Classifier: License :: OSI Approved :: MIT License
Classifier: Programming Language :: Python :: 3
Classifier: Programming Language :: Python :: 3.13
Classifier: Topic :: Software Development :: Libraries
Classifier: Topic :: Utilities
Classifier: Typing :: Typed
Requires-Python: >=3.13
Requires-Dist: aiolimiter>=1.1.0
Requires-Dist: aiosqlite>=0.20.0
Requires-Dist: attrs>=24.2.0
Requires-Dist: authlib<1.6,>=1.5.2
Requires-Dist: bleach>=6.1.0
Requires-Dist: fastapi>=0.110.0
Requires-Dist: fastmcp>=2.10.5
Requires-Dist: filelock>=3.16.0
Requires-Dist: gitpython>=3.1.43
Requires-Dist: httpx[http2]>=0.27.2
Requires-Dist: jinja2>=3.1.4
Requires-Dist: jsonschema>=4.23.0
Requires-Dist: litellm<2,>=1.40.0
Requires-Dist: markdown2>=2.4.12
Requires-Dist: orjson<4,>=3.10.7
Requires-Dist: pathspec>=0.12.1
Requires-Dist: pillow>=10.4.0
Requires-Dist: psutil>=6.1.1
Requires-Dist: pynacl>=1.6.0
Requires-Dist: python-decouple>=3.8
Requires-Dist: pyyaml>=6.0.2
Requires-Dist: redis[hiredis]>=5.3.0
Requires-Dist: rich>=13.9.1
Requires-Dist: ruff>=0.14.1
Requires-Dist: sqlalchemy[asyncio]>=2.0.35
Requires-Dist: sqlmodel>=0.0.16
Requires-Dist: structlog>=24.1.0
Requires-Dist: tenacity>=8.3.0
Requires-Dist: tiktoken>=0.7.0
Requires-Dist: tinycss2>=1.4.0
Requires-Dist: typer>=0.15.0
Requires-Dist: uvicorn[standard]>=0.32.0
Provides-Extra: dev
Requires-Dist: ipython>=8.27.0; extra == 'dev'
Requires-Dist: mypy>=1.11.1; extra == 'dev'
Requires-Dist: pytest-asyncio>=0.23.8; extra == 'dev'
Requires-Dist: pytest-cov>=5.0.0; extra == 'dev'
Requires-Dist: pytest>=8.3.3; extra == 'dev'
Requires-Dist: ruff>=0.5.7; extra == 'dev'
Provides-Extra: postgres
Requires-Dist: asyncpg>=0.30.0; extra == 'postgres'
